mynlp/__init__.py
mynlp/settings.py
mynlp/data/test.dat
mynlp/features/__init__.py
mynlp/features/document.py
mynlp/preprocess/__init__.py
mynlp/preprocess/chineseprocess.py
mynlp/preprocess/englishprocess.py
mynlp/utils/__init__.py
my_nlp-0.12.dist-info/METADATA
my_nlp-0.12.dist-info/WHEEL
my_nlp-0.12.dist-info/top_level.txt
my_nlp-0.12.dist-info/RECORD
