Metadata-Version: 2.1
Name: my-nlp
Version: 0.12
Summary: my nlp toolkit
Home-page: https://github.com/unhappydog/mynlp.git
Author: Xiaolong Liang
Author-email: rembern@126.com
License: UNKNOWN
Platform: UNKNOWN
Requires-Dist: numpy
Requires-Dist: nltk
Requires-Dist: sklearn
Requires-Dist: gensim
